LICENSE
MANIFEST.in
README.rst
requirements.txt
setup.py
SiviCNCDriver.egg-info/PKG-INFO
SiviCNCDriver.egg-info/SOURCES.txt
SiviCNCDriver.egg-info/dependency_links.txt
SiviCNCDriver.egg-info/entry_points.txt
SiviCNCDriver.egg-info/requires.txt
SiviCNCDriver.egg-info/top_level.txt
sivicncdriver/__init__.py
sivicncdriver/__main__.py
sivicncdriver/app.py
sivicncdriver/settings.py
sivicncdriver/configs/example.json
sivicncdriver/gcode/__init__.py
sivicncdriver/gcode/arc_calculator.py
sivicncdriver/gcode/gcode.py
sivicncdriver/gcode/gcode_maker.py
sivicncdriver/serial/__init__.py
sivicncdriver/serial/serial_list.py
sivicncdriver/serial/serial_manager.py
sivicncdriver/serial/thread_read.py
sivicncdriver/serial/thread_send.py
sivicncdriver/ui/__init__.py
sivicncdriver/ui/interface.py
sivicncdriver/ui/main_window.py
sivicncdriver/ui/preprocessor.py
sivicncdriver/ui/preprocessor_window.py
sivicncdriver/ui/ressources_rc.py
sivicncdriver/ui/view3d.py
sivicncdriver/ui/translate/SiviCNCDriver_fr_FR.qm